compchemparser/__init__.py
compchemparser/app.py
compchemparser/main.py
compchemparser/helpers/__init__.py
compchemparser/helpers/ccutils.py
compchemparser/helpers/elements_data.py
compchemparser/helpers/params.py
compchemparser/helpers/utils.py
compchemparser/parsers/__init__.py
compchemparser/parsers/ccgaussian_parser.py
tests/__init__.py
tests/conftest.py
tests/test_parser.py
compchemparser-1.0.2.dist-info/LICENSE
compchemparser-1.0.2.dist-info/METADATA
compchemparser-1.0.2.dist-info/WHEEL
compchemparser-1.0.2.dist-info/entry_points.txt
compchemparser-1.0.2.dist-info/top_level.txt
compchemparser-1.0.2.dist-info/RECORD
