Metadata-Version: 2.1
Name: compchemparser
Version: 1.0.2
Summary: The `compchemparser` package provides parsers to convert quantum chemistry log files into a more condensed JSON format.
Home-page: https://github.com/cambridge-cares/TheWorldAvatar/tree/develop/thermo/CoMoCompChemParser
Author: Daniel Nurkowski and Angiras Menon
Author-email: danieln@cmclinnovations.com
License: MIT
Platform: UNKNOWN
Requires-Python: >=3.5, <4
Requires-Dist: docopt
Requires-Dist: cclib
